mpl_draggable_line/__init__.py
mpl_draggable_line/_line.py
mpl_draggable_line/_version.py
mpl_draggable_line-0.4.1.dist-info/LICENSE
mpl_draggable_line-0.4.1.dist-info/METADATA
mpl_draggable_line-0.4.1.dist-info/WHEEL
mpl_draggable_line-0.4.1.dist-info/top_level.txt
mpl_draggable_line-0.4.1.dist-info/RECORD
